plplugins-1.1.dist-info/METADATA
plplugins-1.1.dist-info/WHEEL
plplugins-1.1.dist-info/RECORD
plplugins/__init__.py
plplugins/extension.abi3.so
