Metadata-Version: 2.4
Name: plplugins
Version: 1.1
Requires-Python: >=3.12
Summary: Collection of utilities for working with Polars
Requires-Dist: polars~=1.36
Requires-Dist: pyarrow>=22.0.0
License-Expression: EUPL-1.2
Project-URL: Repository, https://github.com/slietar/plplugins
